prorca/__init__.py
prorca/anomaly.py
prorca/create_synthetic_data.py
prorca/dag_builder.py
prorca/pathway.py
prorca-0.1.0.dist-info/METADATA
prorca-0.1.0.dist-info/WHEEL
prorca-0.1.0.dist-info/top_level.txt
prorca-0.1.0.dist-info/RECORD
