Metadata-Version: 2.2
Name: prorca
Version: 0.1.0
Summary: ProRCA - Root Cause Analysis Tool
Home-page: https://github.com/profitopsai/ProRCA
Author: Your Team
Author-email: arunks@profitops.ai
Classifier: Programming Language :: Python :: 3
Classifier: License :: OSI Approved :: MIT License
Classifier: Operating System :: OS Independent
Requires-Python: >=3.7
Requires-Dist: numpy
Requires-Dist: pandas
Dynamic: author
Dynamic: author-email
Dynamic: classifier
Dynamic: description
Dynamic: description-content-type
Dynamic: home-page
Dynamic: requires-dist
Dynamic: requires-python
Dynamic: summary
